odoo/addons/analytic_brand/README.rst
odoo/addons/analytic_brand/__init__.py
odoo/addons/analytic_brand/__manifest__.py
odoo/addons/analytic_brand/i18n/analytic_brand.pot
odoo/addons/analytic_brand/i18n/es.po
odoo/addons/analytic_brand/i18n/it.po
odoo/addons/analytic_brand/migrations/18.0.1.1.0/pre-migrate.py
odoo/addons/analytic_brand/models/__init__.py
odoo/addons/analytic_brand/models/res_brand.py
odoo/addons/analytic_brand/readme/CONTRIBUTORS.md
odoo/addons/analytic_brand/readme/DESCRIPTION.md
odoo/addons/analytic_brand/static/description/icon.png
odoo/addons/analytic_brand/static/description/index.html
odoo/addons/analytic_brand/tests/__init__.py
odoo/addons/analytic_brand/tests/test_analytic_brand.py
odoo/addons/analytic_brand/views/res_brand.xml
odoo_addon_analytic_brand-18.0.1.1.0.6.dist-info/METADATA
odoo_addon_analytic_brand-18.0.1.1.0.6.dist-info/WHEEL
odoo_addon_analytic_brand-18.0.1.1.0.6.dist-info/top_level.txt
odoo_addon_analytic_brand-18.0.1.1.0.6.dist-info/RECORD
