Metadata-Version: 2.1
Name: odoo-addon-analytic_brand
Version: 18.0.1.1.0.6
Requires-Python: >=3.10
Requires-Dist: odoo-addon-brand==18.0.*
Requires-Dist: odoo==18.0.*
Requires-Dist: openupgradelib
Summary: This addon associate an analytic account to a brand that will be used as a default value where the brand is used if the analytic accounting is activated
Home-page: https://github.com/OCA/brand
License: AGPL-3
Author: ACSONE SA/NV,Odoo Community Association (OCA)
Author-email: support@odoo-community.org
Classifier: Programming Language :: Python
Classifier: Framework :: Odoo
Classifier: Framework :: Odoo :: 18.0
Classifier: License :: OSI Approved :: GNU Affero General Public License v3
